campay/__init__.py
campay/sdk.py
campay-1.1.0.dist-info/LICENSE
campay-1.1.0.dist-info/METADATA
campay-1.1.0.dist-info/WHEEL
campay-1.1.0.dist-info/top_level.txt
campay-1.1.0.dist-info/RECORD
