Metadata-Version: 2.1
Name: campay
Version: 1.1.0
Summary: Payment Gateway
Home-page: https://github.com/CamPay/campay-python-sdk
Author: CamPay
Author-email: info@campay.net
Project-URL: Bug Tracker, https://github.com/CamPay/campay-python-sdk/issues
Classifier: Programming Language :: Python :: 3
Classifier: License :: OSI Approved :: MIT License
Classifier: Operating System :: OS Independent
Requires-Python: >=3
License-File: LICENSE
